Makefile
README.txt
logo.svg
setup.py
doc/reference/source/changelog.rst
doc/reference/source/conf.py
doc/reference/source/frameworks_integration.rst
doc/reference/source/glossary.rst
doc/reference/source/index.rst
doc/reference/source/installing.rst
doc/reference/source/language_specification.rst
doc/reference/source/logo.png
doc/reference/source/programming_interface.rst
doc/reference/source/_templates/curtain/layout.html
doc/reference/source/_templates/curtain/theme.conf
doc/reference/source/_templates/curtain/static/curtain.css
src/Curtain.egg-info/PKG-INFO
src/Curtain.egg-info/SOURCES.txt
src/Curtain.egg-info/dependency_links.txt
src/Curtain.egg-info/entry_points.txt
src/Curtain.egg-info/requires.txt
src/Curtain.egg-info/top_level.txt
src/curtain/__init__.py
src/curtain/handler.py
src/curtain/processors.py
src/curtain/template.py
src/curtain/bfg/__init__.py
src/curtain/bfg/configure.zcml
src/curtain/tests/__init__.py
src/curtain/tests/__main__.py
src/curtain/tests/attr.ct
src/curtain/tests/attr_1.env
src/curtain/tests/attr_1.xml
src/curtain/tests/c.ct
src/curtain/tests/c_1.env
src/curtain/tests/c_1.xml
src/curtain/tests/condition.ct
src/curtain/tests/condition_1.env
src/curtain/tests/condition_1.xml
src/curtain/tests/condition_2.env
src/curtain/tests/condition_2.xml
src/curtain/tests/content.ct
src/curtain/tests/content_1.env
src/curtain/tests/content_1.xml
src/curtain/tests/defn.ct
src/curtain/tests/defn_1.env
src/curtain/tests/defn_1.xml
src/curtain/tests/error.ct
src/curtain/tests/error_1.env
src/curtain/tests/error_1.xml
src/curtain/tests/hello.ct
src/curtain/tests/hello_wrong.ct
src/curtain/tests/i18n.ct
src/curtain/tests/i18n_1.env
src/curtain/tests/i18n_1.xml
src/curtain/tests/identity.ct
src/curtain/tests/identity_1.env
src/curtain/tests/identity_1.xml
src/curtain/tests/loop.ct
src/curtain/tests/loop_1.env
src/curtain/tests/loop_1.xml
src/curtain/tests/macro.ct
src/curtain/tests/macro_1.env
src/curtain/tests/macro_1.xml
src/curtain/tests/macro_helper.ct
src/curtain/tests/nested_defn.ct
src/curtain/tests/nested_defn_1.env
src/curtain/tests/nested_defn_1.xml
src/curtain/tests/skip.ct
src/curtain/tests/skip_1.env
src/curtain/tests/skip_1.xml
